networkanalysis/__init__.py
networkanalysis/statistics.py
networkanalysis/ergm/__init__.py
networkanalysis/ergm/likelihood.py
networkanalysis/ergm/simulate.py
network_analysis-0.0.1.3.dist-info/LICENCE
network_analysis-0.0.1.3.dist-info/METADATA
network_analysis-0.0.1.3.dist-info/WHEEL
network_analysis-0.0.1.3.dist-info/top_level.txt
network_analysis-0.0.1.3.dist-info/RECORD
