Metadata-Version: 2.1
Name: network-analysis
Version: 0.0.1.3
Summary: Work in progress...
Author-email: Gabriel Fortin-Leblanc <gabriel.fortin-leblanc@umontreal.ca>
Project-URL: Homepage, https://github.com/gabriel-fortin-leblanc/network-analysis
Project-URL: Bug Tracker, https://github.com/gabriel-fortin-leblanc/network-analysis/issues
Classifier: Programming Language :: Python :: 3
Classifier: Operating System :: OS Independent
Requires-Python: >=3.7
License-File: LICENCE
Requires-Dist: scipy (==1.10.1)
Requires-Dist: networkx (==3.0)
Requires-Dist: numpy (==1.24.2)
Requires-Dist: scikit-learn (==1.2.2)
